jfunctions/__init__.py
jfunctions/Validation/__init__.py
jfunctions/Validation/functions.py
jfunctions-0.0.1.dist-info/LICENSE
jfunctions-0.0.1.dist-info/METADATA
jfunctions-0.0.1.dist-info/WHEEL
jfunctions-0.0.1.dist-info/top_level.txt
jfunctions-0.0.1.dist-info/RECORD
